mysqlsmom/__init__.py
mysqlsmom/mysqlsmom.py
mysqlsmom/row_filters.py
mysqlsmom/row_handlers.py
mysqlsmom/config/__init__.py
mysqlsmom/config/example_binlog.py
mysqlsmom/config/example_cron.py
mysqlsmom/config/example_init.py
mysqlsmom/template/__init__.py
mysqlsmom/template/binlog.py
mysqlsmom/template/cron.py
mysqlsmom/template/init.py
mysqlsmom/template/my_handlers.py
mysqlsmom-0.1.7.dist-info/METADATA
mysqlsmom-0.1.7.dist-info/RECORD
mysqlsmom-0.1.7.dist-info/WHEEL
mysqlsmom-0.1.7.dist-info/entry_points.txt
mysqlsmom-0.1.7.dist-info/top_level.txt
